{
  "project_info": {
    "project_number": "415922206465",
    "firebase_url": "https://photographer-matching-default-rtdb.firebaseio.com",
    "project_id": "photographer-matching",
    "storage_bucket": "photographer-matching.appspot.com"
  },
  "client": [
    {
      "client_info": {
        "mobilesdk_app_id": "1:415922206465:android:c2b564fdf83840138dcd00",
        "android_client_info": {
          "package_name": "com.example.final_photographer_matching"
        }
      },
      "oauth_client": [
        {
          "client_id": "415922206465-i1pas74asakt831a7ll5bm94ddkaqqls.apps.googleusercontent.com",
          "client_type": 3
        }
      ],
      "api_key": [
        {
          "current_key": "AIzaSyDKcAGwHIlFR9SvcUkbYPVqwL-p0v28K84"
        }
      ],
      "services": {
        "appinvite_service": {
          "other_platform_oauth_client": [
            {
              "client_id": "415922206465-i1pas74asakt831a7ll5bm94ddkaqqls.apps.googleusercontent.com",
              "client_type": 3
            }
          ]
        }
      }
    },
    {
      "client_info": {
        "mobilesdk_app_id": "1:415922206465:android:2655e5f3c1943c6a8dcd00",
        "android_client_info": {
          "package_name": "wikibook.learnandroid.photographer_matching"
        }
      },
      "oauth_client": [
        {
          "client_id": "415922206465-i1pas74asakt831a7ll5bm94ddkaqqls.apps.googleusercontent.com",
          "client_type": 3
        }
      ],
      "api_key": [
        {
          "current_key": "AIzaSyDKcAGwHIlFR9SvcUkbYPVqwL-p0v28K84"
        }
      ],
      "services": {
        "appinvite_service": {
          "other_platform_oauth_client": [
            {
              "client_id": "415922206465-i1pas74asakt831a7ll5bm94ddkaqqls.apps.googleusercontent.com",
              "client_type": 3
            }
          ]
        }
      }
    }
  ],
  "configuration_version": "1"
}